vault_cert_monitor/__init__.py
vault_cert_monitor/check_vault_certs.py
vault_cert_monitor-0.2.2.dist-info/METADATA
vault_cert_monitor-0.2.2.dist-info/WHEEL
vault_cert_monitor-0.2.2.dist-info/entry_points.txt
vault_cert_monitor-0.2.2.dist-info/RECORD
